zohlathu/__init__.py
zohlathu/lyrics.py
zohlathu-2.1.2.dist-info/LICENSE
zohlathu-2.1.2.dist-info/METADATA
zohlathu-2.1.2.dist-info/WHEEL
zohlathu-2.1.2.dist-info/top_level.txt
zohlathu-2.1.2.dist-info/RECORD
