Metadata-Version: 2.2
Name: zohlathu
Version: 2.1.2
Summary: A Python package for fetching Mizo song lyrics from Zohlathu.in
Home-page: https://github.com/RSR-TG-Info/ZoHlathu
Author: RSR
Author-email: imrsrmizo@gmail.com
Classifier: Programming Language :: Python :: 3
Classifier: License :: OSI Approved :: MIT License
Classifier: Operating System :: OS Independent
Requires-Python: >=3.7
License-File: LICENSE
Requires-Dist: requests
Requires-Dist: feedparser
Requires-Dist: html2text
Requires-Dist: youtube_search
Dynamic: author
Dynamic: author-email
Dynamic: classifier
Dynamic: description
Dynamic: description-content-type
Dynamic: home-page
Dynamic: requires-dist
Dynamic: requires-python
Dynamic: summary
